temporal_kan/__init__.py
temporal_kan/glstm.py
temporal_kan/gr.py
temporal_kan/kan.py
temporal_kan/sltsm.py
temporal_kan/spline.py
temporal_kan/sr.py
temporal_kan-0.1.3.dist-info/METADATA
temporal_kan-0.1.3.dist-info/WHEEL
temporal_kan-0.1.3.dist-info/RECORD
