Metadata-Version: 2.1
Name: temporal_kan
Version: 0.1.3
Summary: Temporal KAN model
Author: Rémi Genet
Requires-Python: >=3.10,<4.0
Classifier: Programming Language :: Python :: 3
Classifier: Programming Language :: Python :: 3.10
Classifier: Programming Language :: Python :: 3.11
Classifier: Programming Language :: Python :: 3.12
Requires-Dist: numpy (>=1.2,<2)
Requires-Dist: pyarrow (>=15.0.0)
Requires-Dist: tensorflow (>=2.8,<3)
